powertool/__init__.py
powertool/cli.py
powertool/powertool.py
powertool-0.2.0.dist-info/DESCRIPTION.rst
powertool-0.2.0.dist-info/METADATA
powertool-0.2.0.dist-info/RECORD
powertool-0.2.0.dist-info/WHEEL
powertool-0.2.0.dist-info/entry_points.txt
powertool-0.2.0.dist-info/metadata.json
powertool-0.2.0.dist-info/top_level.txt
