Metadata-Version: 2.0
Name: powertool
Version: 0.2.0
Summary: Python utility to wake up(wol) and suspend Linux machines remotely
Home-page: https://github.com/raghur/powertool
Author: Raghu Rajagopalan
Author-email: raghu.nospam@gmail.com
License: MIT license
Keywords: powertool
Platform: UNKNOWN
Classifier: Development Status :: 2 - Pre-Alpha
Classifier: Intended Audience :: Developers
Classifier: License :: OSI Approved :: MIT License
Classifier: Natural Language :: English
Classifier: Programming Language :: Python :: 2
Classifier: Programming Language :: Python :: 2.6
Classifier: Programming Language :: Python :: 2.7
Classifier: Programming Language :: Python :: 3
Classifier: Programming Language :: Python :: 3.3
Classifier: Programming Language :: Python :: 3.4
Classifier: Programming Language :: Python :: 3.5
Requires-Dist: Click (>=6.0)
Requires-Dist: coloredlogs
Requires-Dist: wakeonlan
